nonebot_plugin_noadpls/__init__.py
nonebot_plugin_noadpls/__main__.py
nonebot_plugin_noadpls/ban_judge.py
nonebot_plugin_noadpls/config.py
nonebot_plugin_noadpls/data.py
nonebot_plugin_noadpls/ocr/__init__.py
nonebot_plugin_noadpls/ocr/api_ocr.py
nonebot_plugin_noadpls/ocr/ocr.py
nonebot_plugin_noadpls/utils/__init__.py
nonebot_plugin_noadpls/utils/cache.py
nonebot_plugin_noadpls/utils/constants.py
nonebot_plugin_noadpls/utils/log.py
nonebot_plugin_noadpls-0.4.0.dist-info/METADATA
nonebot_plugin_noadpls-0.4.0.dist-info/WHEEL
nonebot_plugin_noadpls-0.4.0.dist-info/licenses/LICENSE
nonebot_plugin_noadpls-0.4.0.dist-info/RECORD
