Metadata-Version: 2.4
Name: nonebot-plugin-noadpls
Version: 0.4.0
Summary: 检测群聊中广告的插件，撤回并禁言，转发管理员
Project-URL: Homepage, https://github.com/LuoChu-NB2Dev/nonebot-plugin-noadpls
Project-URL: Repository, https://github.com/LuoChu-NB2Dev/nonebot-plugin-noadpls
Author-email: gongfuture <gongfuture@outlook.com>
License-Expression: MIT
License-File: LICENSE
Keywords: bot,luochu,nonebot,nonebot2,onebot,onebotv11,qqbot
Classifier: License :: OSI Approved :: MIT License
Classifier: Programming Language :: Python :: 3
Requires-Python: ~=3.10
Requires-Dist: cleanse-speech<0.2,>=0.1.3
Requires-Dist: fuzzywuzzy<0.19,>=0.18.0
Requires-Dist: httpx<1.0.0,>=0.24.0
Requires-Dist: jieba<0.43,>=0.42.1
Requires-Dist: nonebot-adapter-onebot<3,>=2.4.6
Requires-Dist: nonebot-plugin-localstore<0.8,>=0.7.4
Requires-Dist: nonebot2<3,>=2.4.1
Requires-Dist: opencc<2,>=1.1.9
Requires-Dist: paddleocr<3,>=2.10.0
Requires-Dist: paddlepaddle<4,>=3.0.0rc1
Requires-Dist: python-levenshtein<0.28,>=0.27.1
